{
 "attach_print": 0,
 "channel": "Email",
 "creation": "2025-04-28 18:59:50.834461",
 "days_in_advance": 0,
 "docstatus": 0,
 "doctype": "Notification",
 "document_type": "Candidate Portal",
 "enabled": 1,
 "event": "Custom",
 "idx": 0,
 "is_standard": 1,
 "message": "Candidate Portal Link",
 "message_type": "Markdown",
 "modified": "2025-05-06 18:02:42.028137",
 "modified_by": "Administrator",
 "module": "Prompt HR",
 "name": "Candidate Portal Link",
 "owner": "Administrator",
 "recipients": [],
 "send_system_notification": 0,
 "send_to_all_assignees": 1,
 "subject": "Candidate Portal Link"
}