{
 "attach_print": 0,
 "channel": "Email",
 "creation": "2025-04-22 18:34:30.437643",
 "days_in_advance": 0,
 "docstatus": 0,
 "doctype": "Notification",
 "document_type": "Job Applicant",
 "enabled": 1,
 "event": "Custom",
 "idx": 0,
 "is_standard": 1,
 "message": "<p>Dear HR Team,</p>\r\n<p>We would like to inform you that a new job applicant has successfully registered on the system.</p>\r\n<h3>Applicant Details:</h3>\r\n<ul>\r\n   <li><strong>Name:</strong> {{ doc.applicant_name }}</li>\r\n   <li><strong>Email:</strong> {{ doc.email_id }}</li>\r\n   <li><strong>Phone:</strong> {{ doc.phone_number }}</li>\r\n   <li><strong>Position Applied For:</strong> {{ doc.job_title }}</li>\r\n</ul>\r\n<p>Best regards,<br> {{ doc.custom_company }}</p>",
 "message_type": "HTML",
 "modified": "2025-05-08 01:00:02.329285",
 "modified_by": "Administrator",
 "module": "Prompt HR",
 "name": "Job Applicant Registration Mail",
 "owner": "Administrator",
 "recipients": [],
 "send_system_notification": 0,
 "send_to_all_assignees": 1,
 "subject": "New Job Applicant Registered: {{ doc.applicant_name }}"
}