{
 "attach_print": 0,
 "channel": "Email",
 "creation": "2025-05-05 15:13:19.505959",
 "days_in_advance": 0,
 "docstatus": 0,
 "doctype": "Notification",
 "document_type": "Attendance Regularization",
 "enabled": 1,
 "event": "Custom",
 "idx": 0,
 "is_standard": 1,
 "message": "<p>{% set rh_emp = frappe.db.get_value(\"Employee\", doc.employee, \"reports_to\") %}\n{% if rh_emp%}\n    {% set reporting_head = frappe.db.get_value(\"Employee\", rh_emp, \"employee_name\") %}\n{% else %} \n    {% set reporting_head = \"Reporting Head\" %} \n{% endif %}</p>\n\n<p>Dear {{reporting_head}},</p>\n\n<p>I would like to inform you that I have created an Attendance Regularization record for date {{doc.regularization_date.strftime('%d-%m-%Y')}}.<br>\nThe record is now available in the system for your review and necessary action.</p>\n",
 "message_type": "HTML",
 "modified": "2025-05-06 15:12:14.625774",
 "modified_by": "Administrator",
 "module": "Prompt HR",
 "name": "Attendance Regularization Created",
 "owner": "Administrator",
 "recipients": [],
 "send_system_notification": 0,
 "send_to_all_assignees": 1,
 "subject": "Attendance Regularization Created by {{ doc.employee }}"
}